{
  "basics": {
    "name": "Anmol Pahwa",
    "affiliation": "Assistant Professor, Civil Engineering Department, IIT Madras",
    "image": "",
    "email": "xxx@iitm.ac.in",
    "phone": "+91 44 2257 xxxx",
    "url": "https://civil.iitm.ac.in/faculty/xxx/",
    "location": {
      "address": "Room BSB xxx, Building Sciences Block, IIT Madras",
      "postalCode": "600036",
      "city": "Chennai",
      "countryCode": "IN",
      "region": "Tamil Nadu"
    },
    "profiles": [
      {
        "network": "",
        "username": "",
        "url": ""
      }
    ]
  },
  "work": [
    {
      "name": "Civil Engineering Department, IIT Madras",
      "position": "Assistant Professor",
      "url": "https://civil.iitm.ac.in/faculty/xxx/",
      "startDate": "2024",
      "endDate": "",
      "summary": "",
      "highlights": []
    },
    {
      "name": "Institute of Transportation Studies, UC Davis",
      "position": "Postdoctoral Scholar",
      "url": "https://its.ucdavis.edu/people/anmol-pahwa/",
      "startDate": "2023",
      "endDate": "2024",
      "summary": "",
      "highlights": []
    }
  ],
  "education": [
    {
      "institution": "University of California, Davis",
      "location": "Davis CA, USA",
      "url": "https://cee.engineering.ucdavis.edu/",
      "area": "Civil and Environmental Engineering",
      "studyType": "PhD",
      "startDate": "2017",
      "endDate": "2023",
      "score": "4/4",
      "dissertation": "Assessing Sustainability of E-commerce Goods Distribution",
      "courses": []
    },
    {
      "institution": "Indian Institute of Technology - Delhi",
      "location": "Delhi, India",
      "url": "https://civil.iitd.ac.in/",
      "area": "Civil Engineering",
      "studyType": "BTech",
      "startDate": "2013",
      "endDate": "2017",
      "score": "8.33/10.0",
      "dissertation": "Indicators of Reliability and Variability in Bus Systems",
      "courses": []
    }
  ],
  "awards": [
    {
      "title": "Dissertation Grant",
      "date": "2021",
      "awarder": "National Center for Sustainable Transportation",
      "url": "",
      "summary": ""
    },
    {
      "title": "Fellowship",
      "date": "2017",
      "awarder": "National Center for Sustainable Transportation",
      "url": "",
      "summary": ""
    }
  ]
}
